pylint_module_boundaries/__init__.py
pylint_module_boundaries-1.3.1.dist-info/WHEEL
pylint_module_boundaries-1.3.1.dist-info/METADATA
pylint_module_boundaries-1.3.1.dist-info/RECORD
