Metadata-Version: 2.1
Name: pylint-module-boundaries
Version: 1.3.1
Summary: a pylint plugin to enforce restrictions on imports within your project, similar to nx's enforce-module-boundaries eslint plugin 
Home-page: https://github.com/detachhead/pylint-module-boundaries
Author: DetachHead
Author-email: detachhead@users.noreply.github.com
Requires-Python: >=3.11,<4.0
Classifier: Programming Language :: Python :: 3
Classifier: Programming Language :: Python :: 3.11
Requires-Dist: pylint (>=2,<4)
Project-URL: Repository, https://github.com/detachhead/pylint-module-boundaries
